Metadata-Version: 1.1
Name: librpi2caster
Version: 2.0.1
Summary: Common library for rpi2caster utility and drivers
Home-page: http://github.com/elegantandrogyne/librpi2caster
Author: Christophe Catherine Slychan
Author-email: krzysztof.slychan@gmail.com
License: MIT
Platform: UNKNOWN
Classifier: Development Status :: 5 - Production/Stable
Classifier: License :: OSI Approved :: MIT License
Classifier: Natural Language :: English
Classifier: Operating System :: POSIX :: Linux
Classifier: Programming Language :: Python :: 3 :: Only
